touka/__init__.py
touka/callbacks/add.py
touka/callbacks/connect.py
touka/callbacks/version.py
touka/cli.py
touka/database/client.py
touka/database/touka.py
touka/touka.py
touka/utils/os_handler.py
touka/utils/ping.py
touka/utils/validations.py
touka.ssh-2.2.9.dist-info/entry_points.txt
touka.ssh-2.2.9.dist-info/LICENSE
touka.ssh-2.2.9.dist-info/WHEEL
touka.ssh-2.2.9.dist-info/METADATA
touka.ssh-2.2.9.dist-info/RECORD
