Metadata-Version: 2.1
Name: touka.ssh
Version: 2.2.9
Summary: touka.ssh is an ssh manager that allows you to manage all of your VPSs without keeping your password.
Author: anil chauhan
Author-email: anilchauhanxda@gmail.com
Requires-Python: >=3.7,<4.0
Classifier: Programming Language :: Python :: 3
Classifier: Programming Language :: Python :: 3.10
Classifier: Programming Language :: Python :: 3.7
Classifier: Programming Language :: Python :: 3.8
Classifier: Programming Language :: Python :: 3.9
Requires-Dist: prettytable (>=3.3.0,<4.0.0)
Requires-Dist: tinydb (>=4.7.0,<5.0.0)
Requires-Dist: typer (>=0.4.2,<0.5.0)
